[
  {"year": 184, "event": "黄巾起义爆发", "era_name": "中平元年", "type": "military"},
  {"year": 184, "event": "张角病逝，黄巾主力被镇压", "era_name": "中平元年", "type": "military"},
  {"year": 189, "event": "汉灵帝驾崩，少帝刘辩即位", "era_name": "中平六年", "type": "political"},
  {"year": 189, "event": "大将军何进被杀，袁绍诛宦官", "era_name": "中平六年", "type": "political"},
  {"year": 189, "event": "董卓入京，废少帝立献帝", "era_name": "中平六年", "type": "political"},
  {"year": 190, "event": "诸侯讨董，董卓迁都长安", "era_name": "初平元年", "type": "military"},
  {"year": 192, "event": "王允策反吕布刺杀董卓", "era_name": "初平三年", "type": "political"},
  {"year": 192, "event": "李傕郭汜攻入长安，王允被杀", "era_name": "初平三年", "type": "military"},
  {"year": 196, "event": "曹操迎奉天子至许都", "era_name": "建安元年", "type": "political"},
  {"year": 200, "event": "官渡之战，曹操击败袁绍", "era_name": "建安五年", "type": "military"},
  {"year": 202, "event": "袁绍病逝，其子袁谭袁尚相争", "era_name": "建安七年", "type": "political"},
  {"year": 207, "event": "刘备三顾茅庐请诸葛亮出山", "era_name": "建安十二年", "type": "personal"},
  {"year": 207, "event": "诸葛亮提出隆中对战略", "era_name": "建安十二年", "type": "diplomatic"},
  {"year": 208, "event": "赤壁之战，孙刘联军大败曹操", "era_name": "建安十三年", "type": "military"},
  {"year": 210, "event": "周瑜病逝于巴丘", "era_name": "建安十五年", "type": "personal"},
  {"year": 214, "event": "刘备夺取益州，入主成都", "era_name": "建安十九年", "type": "military"},
  {"year": 217, "event": "汉中之战爆发", "era_name": "建安二十二年", "type": "military"},
  {"year": 219, "event": "黄忠阵斩夏侯渊于定军山", "era_name": "建安二十四年", "type": "military"},
  {"year": 219, "event": "刘备进位汉中王", "era_name": "建安二十四年", "type": "political"},
  {"year": 219, "event": "关羽水淹七军，后败走麦城被杀", "era_name": "建安二十四年", "type": "military"},
  {"year": 220, "event": "曹操病逝于洛阳", "era_name": "建安二十五年", "type": "personal"},
  {"year": 220, "event": "曹丕逼汉献帝禅让，建立曹魏", "era_name": "黄初元年", "type": "political"},
  {"year": 221, "event": "刘备在成都称帝，建立蜀汉", "era_name": "章武元年", "type": "political"},
  {"year": 221, "event": "夷陵之战爆发，刘备伐吴", "era_name": "章武元年", "type": "military"},
  {"year": 222, "event": "陆逊火烧连营，夷陵之战蜀汉大败", "era_name": "章武二年", "type": "military"},
  {"year": 223, "event": "刘备病逝白帝城，刘禅继位", "era_name": "章武三年", "type": "political"},
  {"year": 225, "event": "诸葛亮南征，七擒孟获平定南中", "era_name": "建兴三年", "type": "military"},
  {"year": 227, "event": "诸葛亮上出师表，开始北伐", "era_name": "建兴五年", "type": "military"},
  {"year": 228, "event": "街亭之战，马谡失街亭", "era_name": "建兴六年", "type": "military"},
  {"year": 229, "event": "孙权在武昌称帝，建立东吴", "era_name": "黄龙元年", "type": "political"},
  {"year": 234, "event": "诸葛亮病逝五丈原，北伐终止", "era_name": "建兴十二年", "type": "personal"},
  {"year": 249, "event": "高平陵之变，司马懿诛曹爽", "era_name": "正始十年", "type": "political"},
  {"year": 251, "event": "司马懿病逝", "era_name": "嘉平三年", "type": "personal"},
  {"year": 263, "event": "邓艾灭蜀，刘禅出降，蜀汉灭亡", "era_name": "景耀六年", "type": "military"},
  {"year": 265, "event": "司马炎篡魏建立西晋", "era_name": "咸熙二年", "type": "political"},
  {"year": 280, "event": "西晋灭吴，三国归晋", "era_name": "咸宁六年", "type": "military"}
]
